[
  {
    "manufacturer"      :"HP",
    "model"             :"Spectre x360 15-bl000ur",
    "price"             :"700",
    "description"       :"Type: universal, Platform: Intel Kaby Lake, CPU: Intel Core i7, Graphics Card: NVIDIA GeForce 940MX, OS: Windows 10",
    "img0"              :"images/spectre0.jpeg",
    "id"                :"hpspecrtex360",
    "available"         :"In stock"

  },
  {
    "manufacturer"      :"HP",
    "model"             :"ZBook 15 G3",
    "price"             :"750",
    "description"       :"Type: work, Platform: Intel Skylake, CPU: Intel Xeon, Graphics Card: NVIDIA Quadro M2000M, OS: Windows 10",
    "img0"              :"images/ZBook0.png",
    "id"                :"hpzbook",
    "available"         :"Under the order"
  },
  {
    "manufacturer"      :"HP",
    "model"             :"250 G5",
    "price"             :"800",
    "description"       :"Type: work, Platform: Intel Braswell, CPU: Intel Celeron, Graphics Card: Intel HD Graphics 400, OS: DOS",
    "img0"              :"images/hp250g5mini.png",
    "id"                :"hp250g5",
    "available"         :"In stock"
  },
  {
    "manufacturer"      :"HP",
    "model"             :"Pavilion 15-ak073nw ",
    "price"             :"850",
    "description"       :"Type: game, Platform: Intel Skylake, CPU: Intel Core i7, Graphics Card: NVIDIA GeForce GTX 950M, OS: Windows 10",
    "img0"              :"images/hp_pavilion_15ak073nw_0.jpg",
    "id"                :"hppavilion15ak",
    "available"         :"Under the order"
  },
  {
    "manufacturer"      :"HP",
    "model"             :"Pavilion x360 m3-u003dx ",
    "price"             :"850",
    "description"       :"Type: universal, Platform: Intel Skylake, CPU: Intel Core i5, Graphics Card: NVIDIA GeForce GTX 950M, OS: Windows 10",
    "img0"              :"images/Pavilion_x360_0.jpeg",
    "id"                :"hppavilionx360m3",
    "available"         :"In stock"
  },
  {
    "manufacturer"      :"Lenovo",
    "model"             :"Y700-15ISK",
    "price"             :"1241",
    "description"       :"Type: game, Platform: Intel Skylake, CPU: Intel Core i5, Graphics Card: NVIDIA GeForce GTX 960M, OS: Windows 10",
    "img0"              :"images/lenovoy700_15isk_0.jpg",
    "id"                :"lenovoy70015isk",
    "available"         :"Under the order"
  },{
  "manufacturer"      :"Lenovo",
  "model"             :"IdeaPad 510-15IKB ",
  "price"             :"1241",
  "description"       :"Type: game, Platform: Intel Kaby Lake, CPU: Intel Core i3, Graphics Card: NVIDIA GeForce GTX 960M, OS: Windows 8",
  "img0"              :"images/lenovoIdeaPad_510_15IKB_0.png",
  "id"                :"lenovoIdeaPad51015IKB",
  "available"         :"In stock"
},{
  "manufacturer"      :"Lenovo",
  "model"             :"Y700-17 ",
  "price"             :"1280",
  "description"       :"Type: game, Platform: Intel Skylake, CPU: Intel Core i7, Graphics Card: NVIDIA GeForce GTX 960M, OS: Windows 10",
  "img0"              :"images/lenovoY700_17_0.jpg",
  "id"                :"lenovoY70017",
  "available"         :"Under the order"
},{
  "manufacturer"      :"Lenovo",
  "model"             :"G580",
  "price"             :"650",
  "description"       :"Type: universal, Platform: Intel Chief River, CPU: Intel Core i5, Graphics Card: NVIDIA GeForce 610M, OS: DOS",
  "img0"              :"images/lenovoG580_0.jpg",
  "id"                :"lenovoG580",
  "available"         :"In stock"
},{
  "manufacturer"      :"Lenovo",
  "model"             :"Yoga 710",
  "price"             :"650",
  "description"       :"Type: universal, Platform: Intel Kaby Lake, CPU: Intel Core i7, Graphics Card: NVIDIA GeForce 940MX, OS: Windows 10",
  "img0"              :"images/lenovoYoga_710_0.png",
  "id"                :"lenovoYoga710",
  "available"         :"Under the order"
},{
  "manufacturer"      :"Lenovo",
  "model"             :"Yoga 2 Pro",
  "price"             :"1241",
  "description"       :"Type: game, Platform: Intel Skylake, CPU: Intel Core i5, Graphics Card: NVIDIA GeForce GTX 960M, OS: Windows 10",
  "img0"              :"images/lenovoYoga_2_Pro_0.jpg",
  "id"                :"lenovoYoga2Pro",
  "available"         :"In stock"
},{
  "manufacturer"      :"ASUS",
  "model"             :"GL552VW-DM777",
  "price"             :"1500",
  "description"       :"Type: game, Platform: Intel Skylake, CPU: Intel Core i7, Graphics Card: NVIDIA GeForce GTX 960M, OS: Windows 10",
  "img0"              :"images/asusGL552VW_DM777_0.jpg",
  "id"                :"asusGL552VWDM777",
  "available"         :"Under the order"
},{
  "manufacturer"      :"ASUS",
  "model"             :"ZenBook UX510UX-CN108D",
  "price"             :"1500",
  "description"       :"Type: game, Platform: Intel Skylake, CPU: Intel Core i7, Graphics Card: NVIDIA GeForce GTX 950M, OS: Windows 10",
  "img0"              :"images/asusZenBookUX510UX_CN108D_0.jpeg",
  "id"                :"asusZenBookUX510UX",
  "available"         :"In stock"
},{
  "manufacturer"      :"ASUS",
  "model"             :"G701VI BA006T",
  "price"             :"1651",
  "description"       :"Type: game, Platform: Intel Skylake, CPU: Intel Core i7, Graphics Card: NVIDIA GeForce GTX 1080, OS: Windows 10",
  "img0"              :"images/asusG701VI_BA006T_0.jpeg",
  "id"                :"asusG701VIBA006T",
  "available"         :"Under the order"
},{
  "manufacturer"      :"ASUS",
  "model"             :"F540SC-XX100D",
  "price"             :"800",
  "description"       :"Type: universal, Platform: Intel Skylake, CPU: Intel Celeron, Graphics Card: NVIDIA GeForce 810M, OS: DOS",
  "img0"              :"images/asusF540SC_XX100D_0.jpeg",
  "id"                :"asusF540SCXX100D",
  "available"         :"In stock"
},{
  "manufacturer"      :"ASUS",
  "model"             :"R540LJ-XX336T",
  "price"             :"830",
  "description"       :"Type: universal, Platform: Intel Broadwell, CPU: Intel Core i3, Graphics Card: NVIDIA GeForce 920M, OS: Windows 10",
  "img0"              :"images/asusR540LJ_XX336T_0.jpg",
  "id"                :"asusR540LJXX336T",
  "available"         :"Under the order"
},{
  "manufacturer"      :"Dell",
  "model"             :"XPS 15 9560",
  "price"             :"830",
  "description"       :"Type: universal, Platform: Intel Broadwell, CPU: Intel Core i3, Graphics Card: NVIDIA GeForce 920M, OS: Windows 10",
  "img0"              :"images/dell_XPS_15_9560_0.jpeg",
  "id"                :"lenovomodel4",
  "available"         :"In stock"
},{
  "manufacturer"      :"Dell",
  "model"             :"Inspiron 15 3552",
  "price"             :"900",
  "description"       :"Type: universal, Platform: Intel Broadwell, CPU: Intel Celeron, Graphics Card: Intel HD Graphics, OS: Linux",
  "img0"              :"images/dell_Inspiron_15_3552_0.jpg",
  "id"                :"dellInspiron153552",
  "available"         :"Under the order"
},{
  "manufacturer"      :"Dell",
  "model"             :"Alienware 17 R4",
  "price"             :"2012",
  "description"       :"Type: game, Platform: Intel Skylake, CPU: Intel Core i7, Graphics Card: NVIDIA GeForce GTX 1070, OS: Windows 10",
  "img0"              :"images/toshiba_Satellite_Radius_15_0.jpeg",
  "id"                :"toshibaSatelliteRadius15",
  "available"         :"In stock"
},{
  "manufacturer"      :"Toshiba",
  "model"             :"Satellite U840-E1S",
  "price"             :"1720",
  "description"       :"Type: ultrabook, Platform: Intel Chief River, CPU: Intel Core i3, Graphics Card: Intel HD Graphics 3000, OS: Windows 7",
  "img0"              :"images/toshiba_Satellite_U840_E1S_0.jpg",
  "id"                :"toshibaSatelliteU840E1S",
  "available"         :"Under the order"
},{
  "manufacturer"      :"MSI",
  "model"             :"GL62 6QC-473XPL",
  "price"             :"2102",
  "description"       :"Type: game, Platform: Intel Skylake, CPU: Intel Core i5, Graphics Card: NVIDIA GeForce 940MX, OS: Windows 10",
  "img0"              :"images/msiGL62_6QC_473XPL_0.jpg",
  "id"                :"msiGL626QC473XPL",
  "available"         :"In stock"
},{
  "manufacturer"      :"Acer",
  "model"             :"Aspire ES1-533-P2WF",
  "price"             :"740",
  "description"       :"Type: universal, Platform: Intel Apollo Lake, CPU: Intel Pentium, Graphics Card: Intel HD Graphics 505, OS: Linux",
  "img0"              :"images/acer_Aspire_ES1_533_P2WF_0.png",
  "id"                :"acerAspireES1533P2WF",
  "available"         :"Under the order"
},{
  "manufacturer"      :"Acer",
  "model"             :"Extensa 2511G-323A ",
  "price"             :"942",
  "description"       :"Type: universal, Platform: Intel Broadwell, CPU: Intel Core i3, Graphics Card: NVIDIA GeForce 940M, OS: Linux",
  "img0"              :"images/acer_Extensa_2511G_323A _0.jpg",
  "id"                :"acerextensa2511g32a",
  "available"         :"In stock"
},
  {
    "manufacturer"      :"Acer",
    "model"             :"Swift 3 SF314-51-799P",
    "price"             :"1450",
    "description"       :"Type: game, Platform: Intel Skylake, CPU: Intel Core i7, Graphics Card: NVIDIA GeForce GTX 960M, OS: Windows 10",
    "img0"              :"images/acer_Swift_3_SF314_51_799P_0.jpeg",
    "id"                :"acerSwift3SF31451799P",
    "available"         :"Under the order"
  }
]